{
    "orgName": "Salesforce Platform Playground",
    "edition": "Developer",
    "features": [
        "API",
        "AddCustomApps:30",
        "AddCustomObjects:30",
        "AddCustomRelationships:10",
        "AddCustomTabs:30",
        "AssetScheduling:5",
        "AuthorApex",
        "BigObjectsBulkAPI",
        "CaseClassification",
        "CaseWrapUp",
        "ChangeDataCapture",
        "Communities",
        "ContactsToMultipleAccounts",
        "ContractApprovals",
        "CustomNotificationType",
        "DebugApex",
        "DefaultWorkflowUser",
        "DocumentChecklist",
        "DurableClassicStreamingAPI",
        "DurableGenericStreamingAPI",
        "EnableSetPasswordInApi",
        "Entitlements",
        "FieldService:5",
        "FieldServiceDispatcherUser:5",
        "FieldServiceMobileUser:5",
        "FieldServiceSchedulingUser:5",
        "FlowSites",
        "ForceComPlatform",
        "GenericStreaming",
        "Knowledge",
        "LightningSalesConsole",
        "LightningScheduler",
        "LightningServiceConsole",
        "LiveAgent",
        "Macros",
        "MultiCurrency",
        "ObjectLinking",
        "OrderSaveBehaviorBoth",
        "OrderSaveLogicEnabled",
        "PersonAccounts",
        "PlatformCache",
        "ProcessBuilder",
        "ProductsAndSchedules",
        "RecordTypes",
        "S1ClientComponentCacheSize",
        "SalesUser",
        "SalesforceContentUser",
        "ServiceCloud",
        "ServiceUser",
        "SharedActivities",
        "Sites",
        "SocialCustomerService",
        "StateAndCountryPicklist",
        "StreamingAPI",
        "Workflow",
        "WorkflowFlowActionFeature",
        "WorkThanksPref"
    ],
    "settings": {
        "lightningExperienceSettings": {
            "enableS1DesktopEnabled": true
        },
        "mobileSettings": {
            "enableS1EncryptedStoragePref2": false
        }
    }
}
